PyComplexHeatmap/__init__.py
PyComplexHeatmap/_version.py
PyComplexHeatmap/annotations.py
PyComplexHeatmap/clustermap.py
PyComplexHeatmap/colors.py
PyComplexHeatmap/dotHeatmap.py
PyComplexHeatmap/oncoPrint.py
PyComplexHeatmap/utils.py
pycomplexheatmap-1.8.3.dist-info/licenses/LICENSE
pycomplexheatmap-1.8.3.dist-info/METADATA
pycomplexheatmap-1.8.3.dist-info/WHEEL
pycomplexheatmap-1.8.3.dist-info/top_level.txt
pycomplexheatmap-1.8.3.dist-info/RECORD
