Metadata-Version: 2.4
Name: PyComplexHeatmap
Version: 1.8.3
Summary: A python package to plot complex heatmap
Home-page: https://github.com/DingWB/PyComplexHeatmap
Author: Wubin Ding
Author-email: Wubin Ding <ding.wu.bin.gm@gmail.com>
License: MIT License
Project-URL: Homepage, https://github.com/DingWB/PyComplexHeatmap
Project-URL: repository, https://github.com/DingWB/PyComplexHeatmap
Project-URL: Bug Tracker, https://github.com/DingWB/PyComplexHeatmap/issues
Project-URL: documentation, https://dingwb.github.io/PyComplexHeatmap
Keywords: ComplexHeatmap,heatmap
Classifier: Programming Language :: Python :: 3
Classifier: License :: OSI Approved :: MIT License
Classifier: Operating System :: OS Independent
Requires-Python: >=3.0
License-File: LICENSE
Requires-Dist: matplotlib
Requires-Dist: numpy
Requires-Dist: pandas>=1.3.5
Requires-Dist: scipy
Requires-Dist: palettable
Dynamic: author
Dynamic: home-page
Dynamic: license-file
